daxmod/__init__.py
daxmod/access.py
daxmod/constants.py
daxmod/exceptions.py
daxmod/extraction.py
daxmod/persistence.py
daxmod/selection.py
daxmod/utils.py
daxmod/classifiers/__init__.py
daxmod/classifiers/models.py
daxmod/classifiers/pretrained.py
daxmod/classifiers/utils.py
daxmod/predefined/__init__.py
daxmod/predefined/classifiers.py
daxmod/predefined/extractors.py
daxmod-0.1.5.dist-info/LICENSE
daxmod-0.1.5.dist-info/METADATA
daxmod-0.1.5.dist-info/WHEEL
daxmod-0.1.5.dist-info/top_level.txt
daxmod-0.1.5.dist-info/RECORD
